pricelist_parser/__init__.py
pricelist_parser/extruders.py
pricelist_parser/parser.py
pricelist_parser/pricelist_item.py
tests/__init__.py
tests/conftest.py
tests/test_extruders.py
tests/test_items.py
tests/test_parser.py
pricelist_parser-0.2.dist-info/METADATA
pricelist_parser-0.2.dist-info/WHEEL
pricelist_parser-0.2.dist-info/top_level.txt
pricelist_parser-0.2.dist-info/RECORD
