Metadata-Version: 2.1
Name: pricelist-parser
Version: 0.2
Summary: Pricelist parser
Home-page: https://github.com/wondersell/pricelist-parser
Author: Artem Kiselev
Author-email: artem.kiselev@gmail.com
License: UNKNOWN
Platform: UNKNOWN
Classifier: Development Status :: 4 - Beta
Classifier: Intended Audience :: Developers
Classifier: Programming Language :: Python :: 3
Classifier: License :: OSI Approved :: MIT License
Classifier: Operating System :: OS Independent
Requires-Python: >=3.6
Requires-Dist: price-parser (>=0.3.3)
Requires-Dist: xlrd
Requires-Dist: openpyxl
